mseep_openai_tool2mcp-0.0.3.dist-info/licenses/LICENSE
openai_tool2mcp/__init__.py
openai_tool2mcp/cli.py
openai_tool2mcp/foo.py
openai_tool2mcp/server.py
openai_tool2mcp/server_entry.py
openai_tool2mcp/models/__init__.py
openai_tool2mcp/models/mcp.py
openai_tool2mcp/models/openai.py
openai_tool2mcp/openai_client/__init__.py
openai_tool2mcp/openai_client/client.py
openai_tool2mcp/tools/__init__.py
openai_tool2mcp/tools/base.py
openai_tool2mcp/tools/browser.py
openai_tool2mcp/tools/code_interpreter.py
openai_tool2mcp/tools/file_manager.py
openai_tool2mcp/tools/registry.py
openai_tool2mcp/tools/web_search.py
openai_tool2mcp/translator/__init__.py
openai_tool2mcp/translator/mcp_to_openai.py
openai_tool2mcp/translator/openai_to_mcp.py
openai_tool2mcp/utils/__init__.py
openai_tool2mcp/utils/config.py
openai_tool2mcp/utils/errors.py
openai_tool2mcp/utils/logging.py
openai_tool2mcp/utils/security.py
mseep_openai_tool2mcp-0.0.3.dist-info/METADATA
mseep_openai_tool2mcp-0.0.3.dist-info/WHEEL
mseep_openai_tool2mcp-0.0.3.dist-info/entry_points.txt
mseep_openai_tool2mcp-0.0.3.dist-info/top_level.txt
mseep_openai_tool2mcp-0.0.3.dist-info/RECORD
