Metadata-Version: 2.4
Name: mseep-openai-tool2mcp
Version: 0.0.3
Summary: A MCP wrapper server for OpenAI built-in tools. You can use openai search and computer use on Claude APP!
Home-page: 
Author: mseep
Author-email: mseep <support@skydeck.ai>
Maintainer-email: mseep <support@skydeck.ai>
Keywords: python
Classifier: Intended Audience :: Developers
Classifier: Programming Language :: Python
Classifier: Programming Language :: Python :: 3
Classifier: Programming Language :: Python :: 3.10
Classifier: Programming Language :: Python :: 3.11
Classifier: Programming Language :: Python :: 3.12
Classifier: Programming Language :: Python :: 3.13
Classifier: Topic :: Software Development :: Libraries :: Python Modules
Requires-Python: >=3.6
License-File: LICENSE
Requires-Dist: fastapi>=0.100.0
Requires-Dist: uvicorn>=0.23.0
Requires-Dist: pydantic>=2.0.0
Requires-Dist: openai>=1.0.0
Requires-Dist: python-dotenv>=1.0.0
Requires-Dist: requests>=2.0.0
Requires-Dist: mcp[cli]>=1.4.0
Requires-Dist: httpx>=0.28.1
Dynamic: author
Dynamic: license-file
Dynamic: requires-python
